llmsql-0.1.14.dist-info/METADATA
llmsql-0.1.14.dist-info/WHEEL
llmsql-0.1.14.dist-info/entry_points.txt
llmsql-0.1.14.dist-info/licenses/LICENSE
llmsql/__init__.py
llmsql/__main__.py
llmsql/config/config.py
llmsql/evaluation/README.md
llmsql/evaluation/evaluate.py
llmsql/inference/README.md
llmsql/inference/inference_transformers.py
llmsql/inference/inference_vllm.py
llmsql/loggers/__init__.py
llmsql/loggers/logging_config.py
llmsql/prompts/prompts.py
llmsql/utils/__init__.py
llmsql/utils/evaluation_utils.py
llmsql/utils/inference_utils.py
llmsql/utils/regex_extractor.py
llmsql/utils/rich_utils.py
llmsql/utils/utils.py
llmsql-0.1.14.dist-info/RECORD
