Metadata-Version: 2.4
Name: llmsql
Version: 0.1.14
Summary: A Text2SQL benchmark for evaluation of Large Language Models
Keywords: llm,sql,benchmark,evaluation,ai,nlp
Author-Email: Dzmitry Pihulski <dim.pigulsky@gmail.com>
License-File: LICENSE
Classifier: Development Status :: 3 - Alpha
Classifier: Programming Language :: Python :: 3
Classifier: Programming Language :: Python :: 3.10
Classifier: Programming Language :: Python :: 3.11
Classifier: Programming Language :: Python :: 3.12
Classifier: License :: OSI Approved :: MIT License
Classifier: Operating System :: OS Independent
Classifier: Topic :: Scientific/Engineering :: Artificial Intelligence
Project-URL: Homepage, https://llmsql.github.io/llmsql-benchmark/
Project-URL: Repository, https://github.com/LLMSQL/llmsql-benchmark
Project-URL: Documentation, https://llmsql.github.io/llmsql-benchmark/
Project-URL: Issues, https://github.com/LLMSQL/llmsql-benchmark/issues
Requires-Python: >=3.10
Requires-Dist: accelerate>=0.26.0
Requires-Dist: torch>=1.8
Requires-Dist: transformers>=4.1
Requires-Dist: datasets
Requires-Dist: tqdm
Requires-Dist: numpy
Requires-Dist: python-dotenv
Requires-Dist: pyyaml
Requires-Dist: rich
Provides-Extra: dev
Requires-Dist: pytest>=8.4.2; extra == "dev"
Requires-Dist: pytest-cov>=7.0.0; extra == "dev"
Requires-Dist: ruff>=0.13.1; extra == "dev"
Requires-Dist: mypy>=1.18.2; extra == "dev"
Requires-Dist: pre-commit>=4.3.0; extra == "dev"
Requires-Dist: types-tqdm>=4.67.0.20250809; extra == "dev"
Requires-Dist: types-PyYAML>=6.0.12.20250915; extra == "dev"
Requires-Dist: pytest-asyncio>=1.2.0; extra == "dev"
Requires-Dist: sphinx>=8.1.3; extra == "dev"
Requires-Dist: sphinx-autodoc-typehints>=3.0.1; extra == "dev"
Requires-Dist: furo>=2025.9.25; extra == "dev"
Requires-Dist: sphinx-autoapi>=3.6.0; extra == "dev"
Requires-Dist: sphinx-autobuild>=2024.10.3; extra == "dev"
Requires-Dist: sphinx-copybutton>=0.5.2; extra == "dev"
Requires-Dist: pytest-mock>=3.15.1; extra == "dev"
Provides-Extra: vllm
Requires-Dist: vllm>=0.4.2; extra == "vllm"
